aether/__init__.py
aether/__main__.py
aether/bundler.py
aether/cli.py
aether/config.py
aether/rojo_resolver.py
aether/runner.py
aether/utils.py
aether/commands/__init__.py
aether/commands/auth.py
aether/commands/config.py
aether/commands/init.py
aether/commands/run.py
aether/vendor/__init__.py
aether/vendor/testez/Context.lua
aether/vendor/testez/Expectation.lua
aether/vendor/testez/ExpectationContext.lua
aether/vendor/testez/LifecycleHooks.lua
aether/vendor/testez/TestBootstrap.lua
aether/vendor/testez/TestEnum.lua
aether/vendor/testez/TestPlan.lua
aether/vendor/testez/TestPlanner.lua
aether/vendor/testez/TestResults.lua
aether/vendor/testez/TestRunner.lua
aether/vendor/testez/TestSession.lua
aether/vendor/testez/init.lua
aether/vendor/testez/Reporters/TeamCityReporter.lua
aether/vendor/testez/Reporters/TextReporter.lua
aether/vendor/testez/Reporters/TextReporterQuiet.lua
aether_runner-0.3.6.dist-info/licenses/LICENSE
aether_runner-0.3.6.dist-info/METADATA
aether_runner-0.3.6.dist-info/WHEEL
aether_runner-0.3.6.dist-info/entry_points.txt
aether_runner-0.3.6.dist-info/top_level.txt
aether_runner-0.3.6.dist-info/RECORD
