Metadata-Version: 2.4
Name: aether-runner
Version: 0.3.6
Summary: Execute Luau tests on Roblox Cloud
Home-page: https://github.com/yourusername/aether
Author: WildLink Team
Requires-Python: >=3.8
License-File: LICENSE
Requires-Dist: requests>=2.31.0
Requires-Dist: python-dotenv>=1.0.0
Requires-Dist: watchdog>=3.0.0
Requires-Dist: tomli>=2.0.0; python_version < "3.11"
Provides-Extra: dev
Requires-Dist: pytest>=7.0.0; extra == "dev"
Requires-Dist: black>=23.0.0; extra == "dev"
Requires-Dist: mypy>=1.0.0; extra == "dev"
Requires-Dist: pyinstaller>=6.0.0; extra == "dev"
Dynamic: home-page
Dynamic: license-file
Dynamic: requires-python
